hackbot/__init__.py
hackbot/__main__.py
hackbot/cli_args.py
hackbot/commands.py
hackbot/config.py
hackbot/hack.py
hackbot/log_utils.py
hackbot/spinner.py
hackbot/utils.py
hackbot-0.3.0.dist-info/METADATA
hackbot-0.3.0.dist-info/WHEEL
hackbot-0.3.0.dist-info/entry_points.txt
hackbot-0.3.0.dist-info/RECORD
