Metadata-Version: 2.4
Name: hackbot
Version: 0.3.0
Summary: CLI tool for source code analysis using the Hackbot service
Author-email: Hugo Berg <hugo@gatlingx.com>
Requires-Python: >=3.9
Requires-Dist: aiohttp>=3.10.10
Requires-Dist: gitpython>=3.1.43
Requires-Dist: loguru>=0.7.2
Requires-Dist: pydantic>=2.10.6
Requires-Dist: pygithub>=2.5.0
Requires-Dist: pytest-mock>=3.14.0
Requires-Dist: termcolor>=2.0.0
Requires-Dist: tomli>=2.2.1
Requires-Dist: tqdm>=4.67.0
